gscholar/__init__.py
gscholar/__main__.py
gscholar/gscholar.py
gscholar/version.py
gscholar-2.1.0.dist-info/LICENSE
gscholar-2.1.0.dist-info/METADATA
gscholar-2.1.0.dist-info/WHEEL
gscholar-2.1.0.dist-info/entry_points.txt
gscholar-2.1.0.dist-info/top_level.txt
gscholar-2.1.0.dist-info/RECORD
