Metadata-Version: 2.1
Name: gscholar
Version: 2.1.0
Summary: Python library to query Google Scholar.
Home-page: https://github.com/venthur/gscholar
Author: Bastian Venthur
Author-email: mail@venthur.de
License: MIT
Project-URL: Source, https://github.com/venthur/gscholar
Project-URL: Changelog, https://github.com/venthur/gscholar/blob/master/CHANGELOG.md
Keywords: google scholar cli
Requires-Python: >=3.7
License-File: LICENSE
